lsm.cpython-38-darwin.so
lsm_db-0.7.3.dist-info/RECORD
lsm_db-0.7.3.dist-info/WHEEL
lsm_db-0.7.3.dist-info/top_level.txt
lsm_db-0.7.3.dist-info/METADATA
