Metadata-Version: 2.4
Name: lsm-db
Version: 0.7.3
Summary: bindings for the sqlite lsm4 database
Author-email: Charles Leifer <coleifer@gmail.com>
Project-URL: Repository, https://github.com/coleifer/python-lsm-db
Project-URL: Documentation, https://lsm-db.readthedocs.io/
Classifier: Programming Language :: Python :: 2
Classifier: Programming Language :: Python :: 3
Classifier: Topic :: Database :: Database Engines/Servers
Classifier: Topic :: Software Development :: Embedded Systems
Classifier: Topic :: Software Development :: Libraries :: Python Modules
